kgcl_rdflib/README.md
kgcl_rdflib/__init__.py
kgcl_rdflib/apply/__init__.py
kgcl_rdflib/apply/graph_transformer.py
kgcl_rdflib/apply/kgcl_2_sparql.py
kgcl_rdflib/diff/__init__.py
kgcl_rdflib/diff/change_detection.py
kgcl_rdflib/diff/diff_2_kgcl_existential.py
kgcl_rdflib/diff/diff_2_kgcl_single.py
kgcl_rdflib/diff/diff_2_kgcl_triple_annotation.py
kgcl_rdflib/diff/graph_diff.py
kgcl_rdflib/diff/owlstar_sublanguage.py
kgcl_rdflib/diff/pretty_print_kgcl.py
kgcl_rdflib/diff/render_operations.py
kgcl_rdflib/diff/summary_generation.py
kgcl_rdflib/kgcl.py
kgcl_rdflib/kgcl_diff.py
kgcl_rdflib/render_kgcl.py
kgcl_rdflib-0.5.0.dist-info/LICENSE
kgcl_rdflib-0.5.0.dist-info/METADATA
kgcl_rdflib-0.5.0.dist-info/WHEEL
kgcl_rdflib-0.5.0.dist-info/entry_points.txt
kgcl_rdflib-0.5.0.dist-info/RECORD
